odoo8_addon_github_connector_odoo-8.0.0.0.0-py2.7-nspkg.pth
odoo_addons/github_connector_odoo/__openerp__.py
odoo_addons/github_connector_odoo/__init__.py
odoo_addons/github_connector_odoo/README.rst
odoo_addons/github_connector_odoo/security/ir_rule.xml
odoo_addons/github_connector_odoo/security/ir.model.access.csv
odoo_addons/github_connector_odoo/models/odoo_author.py
odoo_addons/github_connector_odoo/models/odoo_module.py
odoo_addons/github_connector_odoo/models/odoo_module_evaluation.py
odoo_addons/github_connector_odoo/models/github_repository_branch.py
odoo_addons/github_connector_odoo/models/odoo_lib_python.py
odoo_addons/github_connector_odoo/models/github_repository.py
odoo_addons/github_connector_odoo/models/odoo_license.py
odoo_addons/github_connector_odoo/models/__init__.py
odoo_addons/github_connector_odoo/models/odoo_module_version.py
odoo_addons/github_connector_odoo/models/odoo_lib_bin.py
odoo_addons/github_connector_odoo/models/github_organization.py
odoo_addons/github_connector_odoo/views/view_odoo_module_evaluation.xml
odoo_addons/github_connector_odoo/views/view_github_organization.xml
odoo_addons/github_connector_odoo/views/action.xml
odoo_addons/github_connector_odoo/views/menu.xml
odoo_addons/github_connector_odoo/views/view_odoo_author.xml
odoo_addons/github_connector_odoo/views/view_odoo_license.xml
odoo_addons/github_connector_odoo/views/view_github_repository_branch.xml
odoo_addons/github_connector_odoo/views/view_odoo_lib_bin.xml
odoo_addons/github_connector_odoo/views/view_odoo_lib_python.xml
odoo_addons/github_connector_odoo/views/view_github_repository.xml
odoo_addons/github_connector_odoo/views/view_odoo_module.xml
odoo_addons/github_connector_odoo/views/view_odoo_module_version.xml
odoo_addons/github_connector_odoo/views/view_reporting.xml
odoo_addons/github_connector_odoo/data/function.xml
odoo_addons/github_connector_odoo/demo/github_organization.xml
odoo8_addon_github_connector_odoo-8.0.0.0.0.dist-info/top_level.txt
odoo8_addon_github_connector_odoo-8.0.0.0.0.dist-info/WHEEL
odoo8_addon_github_connector_odoo-8.0.0.0.0.dist-info/RECORD
odoo8_addon_github_connector_odoo-8.0.0.0.0.dist-info/metadata.json
odoo8_addon_github_connector_odoo-8.0.0.0.0.dist-info/DESCRIPTION.rst
odoo8_addon_github_connector_odoo-8.0.0.0.0.dist-info/METADATA
odoo8_addon_github_connector_odoo-8.0.0.0.0.dist-info/namespace_packages.txt
