Metadata-Version: 2.0
Name: odoo8-addon-github-connector-odoo
Version: 8.0.0.0.0
Summary: Analyze Odoo Modules Informations from github repositories
Home-page: UNKNOWN
Author: UNKNOWN
Author-email: UNKNOWN
License: UNKNOWN
Platform: UNKNOWN
Requires-Dist: odoo (<9.0a,>=8.0a)
Requires-Dist: odoo8-addon-github-connector
Classifier: Programming Language :: Python :: 2.7
Classifier: Framework :: Odoo
